jsonschema_markdown/__init__.py
jsonschema_markdown/main.py
jsonschema_markdown/utils.py
jsonschema_markdown/converter/__init__.py
jsonschema_markdown/converter/markdown.py
jsonschema_markdown-2025.11.0.dist-info/METADATA
jsonschema_markdown-2025.11.0.dist-info/WHEEL
jsonschema_markdown-2025.11.0.dist-info/entry_points.txt
jsonschema_markdown-2025.11.0.dist-info/licenses/LICENSE
jsonschema_markdown-2025.11.0.dist-info/RECORD
