Metadata-Version: 2.4
Name: jsonschema-markdown
Version: 2025.11.0
Summary: Export a JSON Schema document to Markdown documentation.
Project-URL: Repository, https://github.com/elisiariocouto/jsonschema-markdown
Author-email: Elisiário Couto <elisiario@couto.io>
License-Expression: MIT
License-File: LICENSE
Keywords: docs,documentation,json,jsonschema,markdown
Classifier: Development Status :: 4 - Beta
Classifier: Environment :: Console
Classifier: Intended Audience :: Developers
Classifier: Topic :: Documentation
Classifier: Topic :: File Formats :: JSON :: JSON Schema
Classifier: Topic :: Software Development :: Documentation
Classifier: Topic :: Text Processing :: Markup :: Markdown
Classifier: Topic :: Utilities
Requires-Python: >=3.9
Requires-Dist: click<9,>=8.1.7
Requires-Dist: jsonref<2,>=1.1.0
Requires-Dist: loguru>=0.7.2
Requires-Dist: pyyaml<7,>=6.0.2
